[1,["1314174a7@6c48a"],["_textureSource"],["cc.SpriteFrame"],0,[[[{"name":"Double","rect":{"x":944,"y":3,"width":531,"height":28},"offset":{"x":0,"y":0},"originalSize":{"width":531,"height":28},"rotated":true,"capInsets":[0,0,0,0],"packable":true,"pixelsToUnit":100,"pivot":{"x":0.5,"y":0.5},"meshType":0}],[0],0,[0],[0],[0]],[[{"name":"DiamondBg","rect":{"x":369,"y":886,"width":134,"height":142},"offset":{"x":0,"y":0.5},"originalSize":{"width":134,"height":143},"rotated":true,"capInsets":[0,0,0,0],"packable":true,"pixelsToUnit":100,"pivot":{"x":0.5,"y":0.5},"meshType":0}],[0],0,[0],[0],[0]],[[{"name":"CoinBox","rect":{"x":826,"y":812,"width":86,"height":76},"offset":{"x":0,"y":0},"originalSize":{"width":86,"height":76},"rotated":false,"capInsets":[0,0,0,0],"packable":true,"pixelsToUnit":100,"pivot":{"x":0.5,"y":0.5},"meshType":0}],[0],0,[0],[0],[0]],[[{"name":"CircleOutline","rect":{"x":3,"y":472,"width":255,"height":255},"offset":{"x":0,"y":0},"originalSize":{"width":255,"height":255},"rotated":false,"capInsets":[0,0,0,0],"packable":true,"pixelsToUnit":100,"pivot":{"x":0.5,"y":0.5},"meshType":0}],[0],0,[0],[0],[0]],[[{"name":"OutBg","rect":{"x":214,"y":992,"width":23,"height":25},"offset":{"x":0,"y":0},"originalSize":{"width":23,"height":25},"rotated":false,"capInsets":[11,11,11,11],"packable":true,"pixelsToUnit":100,"pivot":{"x":0.5,"y":0.5},"meshType":0}],[0],0,[0],[0],[0]],[[{"name":"AttackBtn","rect":{"x":820,"y":675,"width":131,"height":131},"offset":{"x":0,"y":0},"originalSize":{"width":131,"height":131},"rotated":false,"capInsets":[0,0,0,0],"packable":true,"pixelsToUnit":100,"pivot":{"x":0.5,"y":0.5},"meshType":0}],[0],0,[0],[0],[0]],[[{"name":"Sausage","rect":{"x":271,"y":780,"width":257,"height":100},"offset":{"x":0,"y":0},"originalSize":{"width":257,"height":100},"rotated":false,"capInsets":[0,0,0,0],"packable":true,"pixelsToUnit":100,"pivot":{"x":0.5,"y":0.5},"meshType":0}],[0],0,[0],[0],[0]],[[{"name":"BackHomeBtn","rect":{"x":826,"y":894,"width":79,"height":79},"offset":{"x":0,"y":0},"originalSize":{"width":79,"height":79},"rotated":false,"capInsets":[0,0,0,0],"packable":true,"pixelsToUnit":100,"pivot":{"x":0.5,"y":0.5},"meshType":0}],[0],0,[0],[0],[0]],[[{"name":"Main","rect":{"x":534,"y":772,"width":158,"height":89},"offset":{"x":-3,"y":0.5},"originalSize":{"width":164,"height":90},"rotated":false,"capInsets":[0,0,0,0],"packable":true,"pixelsToUnit":100,"pivot":{"x":0.5,"y":0.5},"meshType":0}],[0],0,[0],[0],[0]],[[{"name":"GreenBtnBg","rect":{"x":531,"y":198,"width":19,"height":21},"offset":{"x":0,"y":0},"originalSize":{"width":19,"height":21},"rotated":false,"capInsets":[9,10,9,10],"packable":true,"pixelsToUnit":100,"pivot":{"x":0.5,"y":0.5},"meshType":0}],[0],0,[0],[0],[0]],[[{"name":"RollIcon","rect":{"x":665,"y":867,"width":155,"height":122},"offset":{"x":0,"y":0},"originalSize":{"width":155,"height":122},"rotated":false,"capInsets":[0,0,0,0],"packable":true,"pixelsToUnit":100,"pivot":{"x":0.5,"y":0.5},"meshType":0}],[0],0,[0],[0],[0]],[[{"name":"FailTitle","rect":{"x":3,"y":3,"width":547,"height":189},"offset":{"x":0,"y":0},"originalSize":{"width":547,"height":189},"rotated":false,"capInsets":[0,0,0,0],"packable":true,"pixelsToUnit":100,"pivot":{"x":0.5,"y":0.5},"meshType":0}],[0],0,[0],[0],[0]],[[{"name":"Time","rect":{"x":185,"y":919,"width":39,"height":37},"offset":{"x":0,"y":0},"originalSize":{"width":39,"height":37},"rotated":false,"capInsets":[20,19,19,18],"packable":true,"pixelsToUnit":100,"pivot":{"x":0.5,"y":0.5},"meshType":0}],[0],0,[0],[0],[0]],[[{"name":"RescueResultTitle","rect":{"x":556,"y":3,"width":528,"height":188},"offset":{"x":0,"y":0},"originalSize":{"width":528,"height":188},"rotated":true,"capInsets":[0,0,0,0],"packable":true,"pixelsToUnit":100,"pivot":{"x":0.5,"y":0.5},"meshType":0}],[0],0,[0],[0],[0]],[[{"name":"InfoBg","rect":{"x":531,"y":745,"width":21,"height":21},"offset":{"x":0,"y":0},"originalSize":{"width":21,"height":21},"rotated":false,"capInsets":[10,10,10,10],"packable":true,"pixelsToUnit":100,"pivot":{"x":0.5,"y":0.5},"meshType":0}],[0],0,[0],[0],[0]],[[{"name":"analog1","rect":{"x":876,"y":540,"width":82,"height":82},"offset":{"x":0,"y":0},"originalSize":{"width":82,"height":82},"rotated":false,"capInsets":[0,0,0,0],"packable":true,"pixelsToUnit":100,"pivot":{"x":0.5,"y":0.5},"meshType":0}],[0],0,[0],[0],[0]],[[{"name":"VictoryTitle","rect":{"x":750,"y":3,"width":528,"height":188},"offset":{"x":0,"y":-0.5},"originalSize":{"width":528,"height":189},"rotated":true,"capInsets":[0,0,0,0],"packable":true,"pixelsToUnit":100,"pivot":{"x":0.5,"y":0.5},"meshType":0}],[0],0,[0],[0],[0]],[[{"name":"FailBg","rect":{"x":277,"y":198,"width":576,"height":121},"offset":{"x":0,"y":0},"originalSize":{"width":576,"height":121},"rotated":true,"capInsets":[0,0,0,0],"packable":true,"pixelsToUnit":100,"pivot":{"x":0.5,"y":0.5},"meshType":0}],[0],0,[0],[0],[0]],[[{"name":"CoinBg","rect":{"x":517,"y":886,"width":134,"height":142},"offset":{"x":0,"y":0},"originalSize":{"width":134,"height":142},"rotated":true,"capInsets":[13,12,12,12],"packable":true,"pixelsToUnit":100,"pivot":{"x":0.5,"y":0.5},"meshType":0}],[0],0,[0],[0],[0]],[[{"name":"Triangle","rect":{"x":185,"y":992,"width":26,"height":23},"offset":{"x":0,"y":0},"originalSize":{"width":26,"height":23},"rotated":true,"capInsets":[0,0,0,0],"packable":true,"pixelsToUnit":100,"pivot":{"x":0.5,"y":0.5},"meshType":0}],[0],0,[0],[0],[0]],[[{"name":"BlueBtnBg","rect":{"x":531,"y":225,"width":19,"height":21},"offset":{"x":0,"y":0},"originalSize":{"width":19,"height":21},"rotated":false,"capInsets":[9,10,9,10],"packable":true,"pixelsToUnit":100,"pivot":{"x":0.5,"y":0.5},"meshType":0}],[0],0,[0],[0],[0]],[[{"name":"Light","rect":{"x":3,"y":198,"width":268,"height":268},"offset":{"x":0.5,"y":-0.5},"originalSize":{"width":269,"height":269},"rotated":false,"capInsets":[0,0,0,0],"packable":true,"pixelsToUnit":100,"pivot":{"x":0.5,"y":0.5},"meshType":0}],[0],0,[0],[0],[0]],[[{"name":"RollBtn","rect":{"x":738,"y":537,"width":132,"height":132},"offset":{"x":0,"y":0},"originalSize":{"width":132,"height":132},"rotated":false,"capInsets":[0,0,0,0],"packable":true,"pixelsToUnit":100,"pivot":{"x":0.5,"y":0.5},"meshType":0}],[0],0,[0],[0],[0]],[[{"name":"Title","rect":{"x":3,"y":919,"width":176,"height":88},"offset":{"x":0,"y":0},"originalSize":{"width":176,"height":88},"rotated":false,"capInsets":[0,0,0,0],"packable":true,"pixelsToUnit":100,"pivot":{"x":0.5,"y":0.5},"meshType":0}],[0],0,[0],[0],[0]],[[{"name":"LockCharacter","rect":{"x":271,"y":886,"width":79,"height":92},"offset":{"x":0,"y":0},"originalSize":{"width":79,"height":92},"rotated":true,"capInsets":[0,0,0,0],"packable":true,"pixelsToUnit":100,"pivot":{"x":0.5,"y":0.5},"meshType":0}],[0],0,[0],[0],[0]],[[{"name":"RemainTime","rect":{"x":3,"y":733,"width":180,"height":232},"offset":{"x":0,"y":0},"originalSize":{"width":180,"height":232},"rotated":true,"capInsets":[0,0,0,0],"packable":true,"pixelsToUnit":100,"pivot":{"x":0.5,"y":0.5},"meshType":0}],[0],0,[0],[0],[0]],[[{"name":"Mask","rect":{"x":698,"y":745,"width":116,"height":116},"offset":{"x":0,"y":0},"originalSize":{"width":116,"height":116},"rotated":false,"capInsets":[0,0,0,0],"packable":true,"pixelsToUnit":100,"pivot":{"x":0.5,"y":0.5},"meshType":0}],[0],0,[0],[0],[0]],[[{"name":"CharacterOutline","rect":{"x":243,"y":980,"width":24,"height":23},"offset":{"x":0,"y":0},"originalSize":{"width":24,"height":23},"rotated":true,"capInsets":[12,12,12,11],"packable":true,"pixelsToUnit":100,"pivot":{"x":0.5,"y":0.5},"meshType":0}],[0],0,[0],[0],[0]],[[{"name":"Tip","rect":{"x":241,"y":733,"width":241,"height":24},"offset":{"x":0,"y":0},"originalSize":{"width":241,"height":24},"rotated":true,"capInsets":[0,0,0,0],"packable":true,"pixelsToUnit":100,"pivot":{"x":0.5,"y":0.5},"meshType":0}],[0],0,[0],[0],[0]],[[{"name":"InnerBg","rect":{"x":185,"y":962,"width":24,"height":26},"offset":{"x":0,"y":0},"originalSize":{"width":24,"height":26},"rotated":true,"capInsets":[10,10,10,12],"packable":true,"pixelsToUnit":100,"pivot":{"x":0.5,"y":0.5},"meshType":0}],[0],0,[0],[0],[0]],[[{"name":"VictoryBg","rect":{"x":404,"y":198,"width":576,"height":121},"offset":{"x":0,"y":0},"originalSize":{"width":576,"height":121},"rotated":true,"capInsets":[0,0,0,0],"packable":true,"pixelsToUnit":100,"pivot":{"x":0.5,"y":0.5},"meshType":0}],[0],0,[0],[0],[0]],[[{"name":"analog2","rect":{"x":531,"y":537,"width":202,"height":201},"offset":{"x":0,"y":-0.5},"originalSize":{"width":202,"height":202},"rotated":true,"capInsets":[0,0,0,0],"packable":true,"pixelsToUnit":100,"pivot":{"x":0.5,"y":0.5},"meshType":0}],[0],0,[0],[0],[0]]]]
