{"importBase":"import","nativeBase":"native","name":"TowerDefense","deps":["main"],"uuids":["09uDoRhrtA+pEAY1/nbTxn","0dI5j4/XNNu6vB/DBzDBpq","15NRTyvjxCG60XwY85Cjjl","1axS/XuwZKEo+p/9LA0bJQ","1cTCmvSu1FQIVw4Q69Yicc","1c6k/9zZtAH7avDra0LyOT","28auD1Xr1NM5Joey8C4lad","29Ll2qB3xNOLdiAsyLY48e","2bKHTr/KVKKKsRXAkppqaR","2cpQGCILdFl7Eheys5MxEN","2eThJwXsxL3KSqWWCwynn4","32Mw5UKWNPKZ+/bVL4FsVG","3c2BJxEZRImq6G7ZXy8XRx","4bxR3qKq9D3rMhwXsdUGnL","50lAlzQrRGrr2Spp51CvVg","53Xk/PZkdGioSMsSHzbpU3","54O8s7USpOeIBU3e1m81R/","57U/LIPhlLZYs+JlTFflCD","58Kx8cwWZFtJU0crVPgJAJ","68KpEmrZBNqb4aaRsOX2Pp","7aBTQ1wq9J+YO1EIcrM4AJ","82rx6A6GhEroVlw6910IDg","87LSIulzlEYppq9FcgXSJ5","99jel8S4JJ75lrwAS2X/ek","a5R/+5l7pLzrwwZV45TLw5","adf7mp8CNAxIElfeiulLWs","dalcmsdmpGd7g7AtZWWKlZ","e4ENvrEYRPkr1HAcfMomng","e5uAJlRbtDFpjnneU0J9wD","09uDoRhrtA+pEAY1/nbTxn@6c48a","09uDoRhrtA+pEAY1/nbTxn@f9941","0dI5j4/XNNu6vB/DBzDBpq@6c48a","0dI5j4/XNNu6vB/DBzDBpq@f9941","15NRTyvjxCG60XwY85Cjjl@6c48a","15NRTyvjxCG60XwY85Cjjl@f9941","1cTCmvSu1FQIVw4Q69Yicc@6c48a","1cTCmvSu1FQIVw4Q69Yicc@f9941","1c6k/9zZtAH7avDra0LyOT@6c48a","1c6k/9zZtAH7avDra0LyOT@f9941","26s6BV6RlErpHUnyvGjuDe","28auD1Xr1NM5Joey8C4lad@6c48a","28auD1Xr1NM5Joey8C4lad@f9941","29Ll2qB3xNOLdiAsyLY48e@6c48a","29Ll2qB3xNOLdiAsyLY48e@f9941","2bKHTr/KVKKKsRXAkppqaR@6c48a","2cpQGCILdFl7Eheys5MxEN@6c48a","2cpQGCILdFl7Eheys5MxEN@f9941","2eDRdxVetBs5MwUxhK1ms0","2eThJwXsxL3KSqWWCwynn4@6c48a","32Mw5UKWNPKZ+/bVL4FsVG@6c48a","32Mw5UKWNPKZ+/bVL4FsVG@f9941","41tEHRXxxBraCRmZ9mOXEX","4bxR3qKq9D3rMhwXsdUGnL@6c48a","50lAlzQrRGrr2Spp51CvVg@6c48a","50lAlzQrRGrr2Spp51CvVg@f9941","52VC87ARdAO4j6I7Kik/Nt","53Xk/PZkdGioSMsSHzbpU3@6c48a","53Xk/PZkdGioSMsSHzbpU3@f9941","55nEqu4R9LR5QRvRNGsEB2","57U/LIPhlLZYs+JlTFflCD@6c48a","58Kx8cwWZFtJU0crVPgJAJ@6c48a","58Kx8cwWZFtJU0crVPgJAJ@f9941","68HBcM48NOQ5jAGq1gUwv4","77FE9jQFtMNInS7pHzqddk","7aBTQ1wq9J+YO1EIcrM4AJ@6c48a","7aBTQ1wq9J+YO1EIcrM4AJ@f9941","82rx6A6GhEroVlw6910IDg@6c48a","82rx6A6GhEroVlw6910IDg@f9941","87LSIulzlEYppq9FcgXSJ5@6c48a","87LSIulzlEYppq9FcgXSJ5@f9941","90CRxL5v1OoIRiF4v6rF7u","99jel8S4JJ75lrwAS2X/ek@6c48a","99jel8S4JJ75lrwAS2X/ek@f9941","9eFA+lSg1Lf4nz71WJXveo","adf7mp8CNAxIElfeiulLWs@6c48a","adf7mp8CNAxIElfeiulLWs@f9941","adoRTrccdDfY1XOb01ghJi","ca0/XYvElM1qZ7q1MrgKCy","d1x/hj0tFEepKGzQw54ycF","dalcmsdmpGd7g7AtZWWKlZ@6c48a","ddxfSfSkRM/rak2BJdSaFA","e4ENvrEYRPkr1HAcfMomng@6c48a","e4ENvrEYRPkr1HAcfMomng@f9941","e5uAJlRbtDFpjnneU0J9wD@6c48a","e5uAJlRbtDFpjnneU0J9wD@f9941","edN0hfnwdC/KXRVDLKnP6L","f3p/hqtH5BzpuzmeOzBsNH","f8bE7f62xH+62WeVWWuL2u","01ab756e1","032b9bce7","03816b11f","03aef2e53","075ba2b92","0e4720f8b","0eee23550","20g1ukYUVPvKWKBRznAKo+@f9941","54TknWPwVPqJqeCR+Y/Czo@f9941","95EkngnxZFbYuFpsqVTaFr@f9941"],"paths":{"0":["Game/images/game/wall",0],"1":["Game/images/game/add_b2",0],"2":["Game/images/game/btn",0],"3":["Game/spines/jiangsi",4],"4":["Game/images/bg2",0],"5":["Game/images/game/add_b1",0],"6":["Game/images/game/add2",0],"7":["Game/images/game/paodan",0],"8":["Game/spines/pigman",0],"9":["Game/images/bg3",0],"10":["Game/spines/tiekuilei",0],"11":["Game/images/game/add_b3",0],"12":["Game/spines/pigman",4],"13":["Game/spines/xiaohei",0],"14":["Game/images/game/lock",0],"15":["Game/images/game/add1",0],"16":["Game/spines/xiaohei",4],"17":["Game/spines/stickman fighter",0],"18":["Game/images/game/hp_p1",0],"19":["Game/spines/stickman fighter",4],"20":["Game/images/game/zidan",0],"21":["Game/images/bg1",0],"22":["Game/images/game/add3",0],"23":["Game/images/game/jiqiang",0],"24":["Game/spines/tiekuilei",4],"25":["Game/images/game/hp_p",0],"26":["Game/spines/jiangsi",0],"27":["Game/images/game/shou",0],"28":["Game/images/game/dapao",0],"29":["Game/images/game/wall/texture",1,1],"30":["Game/images/game/wall/spriteFrame",2,1],"31":["Game/images/game/add_b2/texture",1,1],"32":["Game/images/game/add_b2/spriteFrame",2,1],"33":["Game/images/game/btn/texture",1,1],"34":["Game/images/game/btn/spriteFrame",2,1],"35":["Game/images/bg2/texture",1,1],"36":["Game/images/bg2/spriteFrame",2,1],"37":["Game/images/game/add_b1/texture",1,1],"38":["Game/images/game/add_b1/spriteFrame",2,1],"39":["Game/spines/xiaohei",5],"40":["Game/images/game/add2/texture",1,1],"41":["Game/images/game/add2/spriteFrame",2,1],"42":["Game/images/game/paodan/texture",1,1],"43":["Game/images/game/paodan/spriteFrame",2,1],"44":["Game/spines/pigman/texture",1,1],"45":["Game/images/bg3/texture",1,1],"46":["Game/images/bg3/spriteFrame",2,1],"47":["Game/spines/tiekuilei",5],"48":["Game/spines/tiekuilei/texture",1,1],"49":["Game/images/game/add_b3/texture",1,1],"50":["Game/images/game/add_b3/spriteFrame",2,1],"51":["Game/prefabs/enemy1",3],"52":["Game/spines/xiaohei/texture",1,1],"53":["Game/images/game/lock/texture",1,1],"54":["Game/images/game/lock/spriteFrame",2,1],"55":["Game/spines/pigman",5],"56":["Game/images/game/add1/texture",1,1],"57":["Game/images/game/add1/spriteFrame",2,1],"58":["Game/prefabs/level5",3],"59":["Game/spines/stickman fighter/texture",1,1],"60":["Game/images/game/hp_p1/texture",1,1],"61":["Game/images/game/hp_p1/spriteFrame",2,1],"62":["Game/prefabs/role",3],"63":["Game/prefabs/level3",3],"64":["Game/images/game/zidan/texture",1,1],"65":["Game/images/game/zidan/spriteFrame",2,1],"66":["Game/images/bg1/texture",1,1],"67":["Game/images/bg1/spriteFrame",2,1],"68":["Game/images/game/add3/texture",1,1],"69":["Game/images/game/add3/spriteFrame",2,1],"70":["Game/prefabs/level1",3],"71":["Game/images/game/jiqiang/texture",1,1],"72":["Game/images/game/jiqiang/spriteFrame",2,1],"73":["UI/prefabs/TowerDefenseView",3],"74":["Game/images/game/hp_p/texture",1,1],"75":["Game/images/game/hp_p/spriteFrame",2,1],"76":["Game/prefabs/level11",3],"77":["Game/spines/stickman fighter",5],"78":["Game/prefabs/level4",3],"79":["Game/spines/jiangsi/texture",1,1],"80":["Game/prefabs/bullet0",3],"81":["Game/images/game/shou/texture",1,1],"82":["Game/images/game/shou/spriteFrame",2,1],"83":["Game/images/game/dapao/texture",1,1],"84":["Game/images/game/dapao/spriteFrame",2,1],"85":["Game/prefabs/level6",3],"86":["Game/prefabs/level0",3],"87":["Game/spines/jiangsi",5]},"scenes":{},"packs":{"01ab756e1":["65","80"],"032b9bce7":["31","35","37","44","45","48","52","64","29","66","40","42","56","60","68","71","59","49","33","53","74","79","83","81"],"03816b11f":["46","73","82"],"03aef2e53":["1","4","5","8","9","10","13","20","0","21","6","7","15","18","22","23","17","11","2","14","25","26","28","27"],"075ba2b92":["51","55"],"0e4720f8b":["61","62","75","77"],"0eee23550":["30","32","38","41","50","57","69","72","86"]},"versions":{"import":[88,"8b82e",89,"b87ae",90,"de2e4",91,"e46ca",92,"022e0",93,"64fad",94,"b33cc",34,"0b3eb",3,"83590",36,"a282a",39,"c630b",43,"34e07",47,"955f3",12,"fe2e7",54,"3325c",16,"4c745",58,"a8a1b",19,"6b79f",63,"9663f",67,"2cca2",70,"758cc",24,"03991",76,"9d784",78,"078f1",84,"fabc7",85,"b8198",87,"81605"],"native":[0,"fab6a",1,"67e7d",2,"717fc",3,"93915",4,"19e2a",5,"a57d5",6,"82480",7,"bd426",8,"8d37a",9,"71792",10,"3f63e",11,"c7b63",12,"b0509",13,"ce6ef",14,"4d87d",15,"b05ab",16,"64772",17,"81c66",18,"5f631",19,"5ab03",20,"b4146",21,"fa212",22,"a744f",23,"0822a",24,"ec872",25,"21f8f",26,"f12f9",27,"f74c7",28,"4b106"]},"redirect":[95,"0",96,"0",97,"0"],"debug":false,"extensionMap":{},"types":["cc.ImageAsset","cc.Texture2D","cc.SpriteFrame","cc.Prefab","cc.Asset","sp.SkeletonData"]}