[{"__type__":"cc.SpriteFrame","content":{"name":"中间","texture":"181fUq9hBGXpgxXCfvSqno","rect":[4,49,148,39],"offset":[0,0],"originalSize":[148,39],"capInsets":[0,0,0,0]}},{"__type__":"cc.SpriteAtlas","_name":"new_floor_plist.plist","_spriteFrames":{"中间":{"__uuid__":"1bO8nMPYNKwJhzIQy/CBbS"},"头部":{"__uuid__":"a9XFv4Z+hMPZ075dmDuhMx"},"尾部 ":{"__uuid__":"31bwkmJOlLG539wTIAGkzx"},"尾部":{"__uuid__":"6eAHu+vmFBAIsfW4m/SQ/P"}}},{"__type__":"cc.SpriteFrame","content":{"name":"尾部 ","texture":"181fUq9hBGXpgxXCfvSqno","rect":[4,94,148,37],"offset":[0,0],"originalSize":[148,37],"capInsets":[0,0,0,0]}},{"__type__":"cc.SpriteFrame","content":{"name":"尾部","texture":"181fUq9hBGXpgxXCfvSqno","rect":[4,4,148,39],"offset":[0,0],"originalSize":[148,39],"capInsets":[0,0,0,0]}},{"__type__":"cc.SpriteFrame","content":{"name":"头部","texture":"181fUq9hBGXpgxXCfvSqno","rect":[158,4,148,39],"offset":[0,0],"originalSize":[148,39],"rotated":1,"capInsets":[0,0,0,0]}}]